<?xml version="1.0" encoding="UTF-8"?>
<databaseChangeLog
    xmlns="http://www.liquibase.org/xml/ns/dbchangelog"
    xmlns:xsi="http://www.w3.org/2001/XMLSchema-instance"
    xsi:schemaLocation="http://www.liquibase.org/xml/ns/dbchangelog
        http://www.liquibase.org/xml/ns/dbchangelog/dbchangelog-4.23.xsd">

    <changeSet id="0002-create-consent-policies-table" author="healthdata-system">
        <comment>Create consent policies table for organization-level consent rules</comment>

        <createTable tableName="consent_policies">
            <column name="id" type="uuid">
                <constraints primaryKey="true" nullable="false"/>
            </column>
            <column name="tenant_id" type="varchar(64)">
                <constraints nullable="false"/>
            </column>
            <column name="policy_name" type="varchar(255)">
                <constraints nullable="false"/>
            </column>
            <column name="policy_type" type="varchar(50)">
                <constraints nullable="false"/>
            </column>
            <column name="description" type="text">
                <constraints nullable="true"/>
            </column>
            <column name="rules" type="text">
                <constraints nullable="false"/>
            </column>
            <column name="priority" type="integer" defaultValueNumeric="0">
                <constraints nullable="false"/>
            </column>
            <column name="active" type="boolean" defaultValueBoolean="true">
                <constraints nullable="false"/>
            </column>
            <column name="created_at" type="timestamp with time zone" defaultValueComputed="CURRENT_TIMESTAMP">
                <constraints nullable="false"/>
            </column>
            <column name="updated_at" type="timestamp with time zone" defaultValueComputed="CURRENT_TIMESTAMP">
                <constraints nullable="false"/>
            </column>
        </createTable>

        <addUniqueConstraint
            tableName="consent_policies"
            columnNames="tenant_id, policy_name"
            constraintName="uk_consent_policy_name"/>

        <createIndex indexName="idx_consent_policies_tenant" tableName="consent_policies">
            <column name="tenant_id"/>
        </createIndex>

        <createIndex indexName="idx_consent_policies_type" tableName="consent_policies">
            <column name="policy_type"/>
        </createIndex>

        <rollback>
            <dropTable tableName="consent_policies"/>
        </rollback>
    </changeSet>

</databaseChangeLog>
